sdk_pytest_checkmate/__init__.py
sdk_pytest_checkmate/_config.py
sdk_pytest_checkmate/_constants.py
sdk_pytest_checkmate/_context.py
sdk_pytest_checkmate/_core.py
sdk_pytest_checkmate/_http_client.py
sdk_pytest_checkmate/_json_validator.py
sdk_pytest_checkmate/_models.py
sdk_pytest_checkmate/_plugin.py
sdk_pytest_checkmate/_report_generator.py
sdk_pytest_checkmate/_types.py
sdk_pytest_checkmate/py.typed
sdk_pytest_checkmate-0.4.0a3.dist-info/METADATA
sdk_pytest_checkmate-0.4.0a3.dist-info/WHEEL
sdk_pytest_checkmate-0.4.0a3.dist-info/entry_points.txt
sdk_pytest_checkmate-0.4.0a3.dist-info/licenses/LICENSE
sdk_pytest_checkmate-0.4.0a3.dist-info/RECORD
