Metadata-Version: 2.4
Name: sdk-pytest-checkmate
Version: 0.4.0a3
Summary: Advanced pytest-based testing framework for QA engineers and test automation specialists.
Project-URL: Homepage, https://github.com/o73k51i/sdk-pytest-checkmate
Project-URL: Documentation, https://github.com/o73k51i/sdk-pytest-checkmate/blob/main/docs/main.md
Project-URL: Repository, https://github.com/o73k51i/sdk-pytest-checkmate.git
Project-URL: Bug Tracker, https://github.com/o73k51i/sdk-pytest-checkmate/issues
Author-email: o73k51i <o73k51i@proton.me>
License: MIT License
License-File: LICENSE
Keywords: api-testing,async-testing,automation-framework,environment-management,epic-story,html-reports,http-client,json-schema,pytest,qa,quality-assurance,soft-assertions,test-automation,test-framework,test-organization,test-reporting,test-steps,test-validation,testing
Classifier: Development Status :: 4 - Beta
Classifier: Framework :: Pytest
Classifier: Intended Audience :: Developers
Classifier: License :: OSI Approved :: MIT License
Classifier: Operating System :: OS Independent
Classifier: Programming Language :: Python
Classifier: Programming Language :: Python :: 3
Classifier: Programming Language :: Python :: 3.10
Classifier: Programming Language :: Python :: 3.11
Classifier: Programming Language :: Python :: 3.12
Classifier: Programming Language :: Python :: 3.13
Classifier: Topic :: Software Development :: Quality Assurance
Classifier: Topic :: Software Development :: Testing
Requires-Python: <3.14,>=3.10
Requires-Dist: httpx>=0.28.1
Requires-Dist: jsonschema>=4.25.1
Requires-Dist: pytest-asyncio>=1.1.0
Requires-Dist: pytest>=8.4.1
